{
  "main": {
    "id": "4f1fb63d95f1f2a3",
    "type": "split",
    "children": [
      {
        "id": "6d24c309b75aeb28",
        "type": "tabs",
        "children": [
          {
            "id": "e1169908a5024cd9",
            "type": "leaf",
            "state": {
              "type": "markdown",
              "state": {
                "file": "Java/Security/Spring Security with RBAC.md",
                "mode": "source",
                "source": false
              },
              "icon": "lucide-file",
              "title": "Spring Security with RBAC"
            }
          }
        ]
      }
    ],
    "direction": "vertical"
  },
  "left": {
    "id": "8ac2132eacb7f37c",
    "type": "split",
    "children": [
      {
        "id": "aceda510d62302f5",
        "type": "tabs",
        "children": [
          {
            "id": "c6297d84f9dd664c",
            "type": "leaf",
            "state": {
              "type": "search",
              "state": {
                "query": "",
                "matchingCase": false,
                "explainSearch": false,
                "collapseAll": false,
                "extraContext": false,
                "sortOrder": "alphabetical"
              },
              "icon": "lucide-search",
              "title": "Search"
            }
          },
          {
            "id": "28b9d6ce7435d057",
            "type": "leaf",
            "state": {
              "type": "bookmarks",
              "state": {},
              "icon": "lucide-bookmark",
              "title": "Bookmarks"
            }
          },
          {
            "id": "10dd90ec8a7b76cb",
            "type": "leaf",
            "state": {
              "type": "file-explorer",
              "state": {
                "sortOrder": "alphabetical",
                "autoReveal": false
              },
              "icon": "lucide-folder-closed",
              "title": "Files"
            }
          }
        ],
        "currentTab": 2
      }
    ],
    "direction": "horizontal",
    "width": 244.50390243530273
  },
  "right": {
    "id": "499b88f4d782a22f",
    "type": "split",
    "children": [
      {
        "id": "4c1a1aa03baa1ecf",
        "type": "tabs",
        "children": [
          {
            "id": "33e351c2ca471be5",
            "type": "leaf",
            "state": {
              "type": "backlink",
              "state": {
                "file": "Message Queue/Kafka/Python producer 腳本建立.md",
                "collapseAll": false,
                "extraContext": false,
                "sortOrder": "alphabetical",
                "showSearch": true,
                "searchQuery": "",
                "backlinkCollapsed": false,
                "unlinkedCollapsed": false
              },
              "icon": "links-coming-in",
              "title": "Backlinks for Python producer 腳本建立"
            }
          },
          {
            "id": "bbed73c3f59c24b6",
            "type": "leaf",
            "state": {
              "type": "outgoing-link",
              "state": {
                "file": "Message Queue/Kafka/Python producer 腳本建立.md",
                "linksCollapsed": false,
                "unlinkedCollapsed": false
              },
              "icon": "links-going-out",
              "title": "Outgoing links from Python producer 腳本建立"
            }
          },
          {
            "id": "cd5412df3d31c6fb",
            "type": "leaf",
            "state": {
              "type": "tag",
              "state": {
                "sortOrder": "frequency",
                "useHierarchy": true
              },
              "icon": "lucide-tags",
              "title": "Tags"
            }
          },
          {
            "id": "04bb78368635fbea",
            "type": "leaf",
            "state": {
              "type": "outline",
              "state": {
                "file": "Message Queue/Kafka/Python producer 腳本建立.md"
              },
              "icon": "lucide-list",
              "title": "Outline of Python producer 腳本建立"
            }
          },
          {
            "id": "22d1196cdaf39f9b",
            "type": "leaf",
            "state": {
              "type": "all-properties",
              "state": {
                "sortOrder": "frequency",
                "showSearch": false,
                "searchQuery": ""
              },
              "icon": "lucide-archive",
              "title": "All properties"
            }
          },
          {
            "id": "42a39a0b4e54a379",
            "type": "leaf",
            "state": {
              "type": "advanced-tables-toolbar",
              "state": {},
              "icon": "spreadsheet",
              "title": "Advanced Tables"
            }
          }
        ],
        "currentTab": 5
      }
    ],
    "direction": "horizontal",
    "width": 279.5,
    "collapsed": true
  },
  "left-ribbon": {
    "hiddenItems": {
      "obsidian-excalidraw-plugin:Create new drawing": false,
      "switcher:Open quick switcher": false,
      "graph:Open graph view": false,
      "canvas:Create new canvas": false,
      "daily-notes:Open today's daily note": false,
      "templates:Insert template": false,
      "command-palette:Open command palette": false,
      "omnisearch:Omnisearch": false,
      "table-editor-obsidian:Advanced Tables Toolbar": false
    }
  },
  "active": "e1169908a5024cd9",
  "lastOpenFiles": [
    "Java/Security/Spring Security Note By Gemini.md",
    "Java/Security/Security 與 WebConfigurer 的 CORS 設定.md",
    "Network/cookie、localStorage、sessionStorage、indexedDB.md",
    "Java/BigDecimal.md",
    "Format/ISO 8601.md",
    "Database/MySQL/MySQL MATCH...AGAINST 用法.md",
    "Java/Spring Batch.md",
    "Network/Authentication - JWT.md",
    "Network/Webhook 簡介.md",
    "Network/Todo.md",
    "Network/Forward proxy and Reverse Proxy.md",
    "Network/Github login.md",
    "Network/OAuth.md",
    "Network/Path Parameters vs Query Parameters.md",
    "Obsidian/列出當前 folder 下的所有 tasks.md",
    "Container/Docker/Docker-compose.md",
    "Container/Docker/docker.canvas",
    "Container/Docker/忽略特定檔案 .dockerignore.md",
    "Container/Docker/將 docker image push 到 docker hub.md",
    "Container/Docker/在本地檔案和容器間傳遞資料.md",
    "Java/手動進行 transaction.md",
    "Java/Java Local 系列時間用法.md",
    "Java/Lambda expression.md",
    "Java/Untitled 1.md",
    "Java/Spring Boot/Spring Boot Basic.md",
    "Java/application.properties 讀取環境變數 (intellij).md",
    "Git/git檔案還原.md",
    "Untitled.canvas",
    "Pasted image 20250715152313.png",
    "AI",
    "image/JVM_runtime_data_area.png",
    "image/JVM_rumtime_data_area.png",
    "Java/JVM",
    "Git/git.canvas",
    "Misc/Java",
    "Misc",
    "Container/Docker/Run Container",
    "Java/RedisTemplate",
    "Algo & DS/Tree",
    "AWS/AWS 操作",
    "Algo & DS/Sorting",
    "Algo & DS",
    "image/access_level_modifiers.png",
    "image/envfile.png",
    "image/env.png",
    "image/router_path.png",
    "image/Vue-Lifecycle.png",
    "image/v-directive.png",
    "image/MVVM.png",
    "Untitled 1.canvas",
    "NodeJS/NestJS/NestJS.canvas",
    "Frontend/CSS/CSS.canvas",
    "Frontend/ReactJS/React.canvas",
    "SWE/API.canvas",
    "Cache/redis.canvas",
    "IoT/Untitled.canvas"
  ]
}